lavague/llms/huggingface/__init__.py
lavague/llms/huggingface/base.py
lavague_llms_huggingface-0.1.0.dist-info/METADATA
lavague_llms_huggingface-0.1.0.dist-info/WHEEL
lavague_llms_huggingface-0.1.0.dist-info/RECORD
