Metadata-Version: 2.1
Name: lavague-llms-huggingface
Version: 0.1.0
Summary: HuggingFaceLLM integration for lavague
Home-page: https://lavague.ai
License: Apache-2.0
Keywords: LAM,action,automation,LLM,NLP,RAG,selenium,playwright
Author: lavague-ai
Requires-Python: >=3.8.1,<4.0.0
Classifier: Development Status :: 3 - Alpha
Classifier: Intended Audience :: Developers
Classifier: License :: OSI Approved :: Apache Software License
Classifier: Programming Language :: Python :: 3
Classifier: Programming Language :: Python :: 3.9
Classifier: Programming Language :: Python :: 3.10
Classifier: Programming Language :: Python :: 3.11
Classifier: Programming Language :: Python :: 3.12
Classifier: Topic :: Scientific/Engineering :: Artificial Intelligence
Classifier: Topic :: Software Development :: Libraries :: Application Frameworks
Classifier: Topic :: Software Development :: Libraries :: Python Modules
Requires-Dist: accelerate (>=0.30.0,<0.31.0)
Requires-Dist: bitsandbytes (>=0.43.1,<0.44.0)
Requires-Dist: lavague-core (>=0.1.0,<0.2.0)
Requires-Dist: llama-index-llms-huggingface (>=0.1.5,<0.2.0)
Project-URL: Documentation, https://docs.lavague.ai/en/latest/
Project-URL: Repository, https://github.com/lavague-ai/LaVague/
